domain_suffixes/__init__.py
domain_suffixes/skeleton.py
domain_suffixes/suffix_parser.py
domain_suffixes/suffixes.py
domain_suffixes/tld_ranks.py
domain_suffixes/tld_reg_date_parser.py
domain_suffixes/tld_reg_dates_v1.txt
domain_suffixes/trie.py
domain_suffixes-1.1.3.dist-info/LICENSE.txt
domain_suffixes-1.1.3.dist-info/METADATA
domain_suffixes-1.1.3.dist-info/WHEEL
domain_suffixes-1.1.3.dist-info/top_level.txt
domain_suffixes-1.1.3.dist-info/RECORD
