Metadata-Version: 2.1
Name: domain-suffixes
Version: 1.1.3
Summary: Library to download and use the latest set of TLDs and public multi label domain suffixes from IANA and ICANN
Home-page: https://github.com/jconwell/domain_suffixes/
Author: John Conwell
Author-email: john@iamjohn.me
License: MIT
Project-URL: Documentation, https://github.com/jconwell/domain_suffixes/
Project-URL: Source, https://github.com/jconwell/domain_suffixes/tree/master/domain_suffixes
Project-URL: Changelog, https://github.com/jconwell/domain_suffixes/blob/master/CHANGELOG.rst
Project-URL: Download, https://pypi.org/project/domain_suffixes/#files
Platform: any
Classifier: Development Status :: 4 - Beta
Classifier: Programming Language :: Python
License-File: LICENSE.txt
Requires-Dist: requests (<3.0,>=2.2)
Requires-Dist: bs4
Requires-Dist: unidecode
Requires-Dist: tranco
Requires-Dist: importlib-metadata ; python_version < "3.8"
Provides-Extra: testing
Requires-Dist: setuptools ; extra == 'testing'
Requires-Dist: pytest ; extra == 'testing'
Requires-Dist: pytest-cov ; extra == 'testing'
